ai_sdlc/__init__.py
ai_sdlc/cli.py
ai_sdlc/utils.py
ai_sdlc/commands/__init__.py
ai_sdlc/commands/done.py
ai_sdlc/commands/init.py
ai_sdlc/commands/new.py
ai_sdlc/commands/next.py
ai_sdlc/commands/status.py
ai_sdlc/scaffold_template/.aisdlc
ai_sdlc/scaffold_template/prompts/0.idea.instructions.md
ai_sdlc/scaffold_template/prompts/1.prd.instructions.md
ai_sdlc/scaffold_template/prompts/2.prd-plus.instructions.md
ai_sdlc/scaffold_template/prompts/3.system-template.instructions.md
ai_sdlc/scaffold_template/prompts/4.systems-patterns.instructions.md
ai_sdlc/scaffold_template/prompts/5.tasks.instructions.md
ai_sdlc/scaffold_template/prompts/6.tasks-plus.instructions.md
ai_sdlc/scaffold_template/prompts/7.tests.instructions.md
ai_sdlc-0.6.3.data/data/ai_sdlc/scaffold_template/.aisdlc
ai_sdlc-0.6.3.data/data/ai_sdlc/scaffold_template/prompts/0.idea.instructions.md
ai_sdlc-0.6.3.data/data/ai_sdlc/scaffold_template/prompts/1.prd.instructions.md
ai_sdlc-0.6.3.data/data/ai_sdlc/scaffold_template/prompts/2.prd-plus.instructions.md
ai_sdlc-0.6.3.data/data/ai_sdlc/scaffold_template/prompts/3.system-template.instructions.md
ai_sdlc-0.6.3.data/data/ai_sdlc/scaffold_template/prompts/4.systems-patterns.instructions.md
ai_sdlc-0.6.3.data/data/ai_sdlc/scaffold_template/prompts/5.tasks.instructions.md
ai_sdlc-0.6.3.data/data/ai_sdlc/scaffold_template/prompts/6.tasks-plus.instructions.md
ai_sdlc-0.6.3.data/data/ai_sdlc/scaffold_template/prompts/7.tests.instructions.md
ai_sdlc-0.6.3.dist-info/METADATA
ai_sdlc-0.6.3.dist-info/WHEEL
ai_sdlc-0.6.3.dist-info/entry_points.txt
ai_sdlc-0.6.3.dist-info/licenses/LICENSE
ai_sdlc-0.6.3.dist-info/RECORD
