Metadata-Version: 2.4
Name: ai-sdlc
Version: 0.6.3
Summary: Markdown-driven SDLC with AI agent chaining.
Project-URL: Homepage, https://github.com/ParkerRex/ai-sdlc
Project-URL: Repository, https://github.com/ParkerRex/ai-sdlc
Project-URL: Documentation, https://github.com/ParkerRex/ai-sdlc#readme
Project-URL: Changelog, https://github.com/ParkerRex/ai-sdlc/blob/main/CHANGELOG.md
Project-URL: Bug Tracker, https://github.com/ParkerRex/ai-sdlc/issues
Author-email: Parker Rex <me@parkerrex.com>
License-Expression: MIT
License-File: LICENSE
Keywords: ai,automation,cli,development,markdown,sdlc,workflow
Classifier: Development Status :: 4 - Beta
Classifier: Environment :: Console
Classifier: Intended Audience :: Developers
Classifier: Operating System :: OS Independent
Classifier: Programming Language :: Python :: 3
Classifier: Programming Language :: Python :: 3.11
Classifier: Programming Language :: Python :: 3.12
Classifier: Programming Language :: Python :: 3.13
Classifier: Topic :: Software Development
Classifier: Topic :: Software Development :: Documentation
Classifier: Topic :: Software Development :: Quality Assurance
Classifier: Topic :: Utilities
Requires-Python: >=3.11.0
Requires-Dist: tomli>=1.2.0; python_version < '3.11'
Provides-Extra: dev
Requires-Dist: bandit>=1.7.0; extra == 'dev'
Requires-Dist: build>=0.10.0; extra == 'dev'
Requires-Dist: mypy>=1.0; extra == 'dev'
Requires-Dist: pyright>=1.1.350; extra == 'dev'
Requires-Dist: pytest-asyncio>=0.21.0; extra == 'dev'
Requires-Dist: pytest-cov>=4.0; extra == 'dev'
Requires-Dist: pytest-mock>=3.0; extra == 'dev'
Requires-Dist: pytest>=7.0; extra == 'dev'
Requires-Dist: ruff>=0.0.292; extra == 'dev'
Requires-Dist: safety>=2.0.0; extra == 'dev'
Requires-Dist: twine>=4.0.0; extra == 'dev'
